pipecat_audio_llm/__init__.py
pipecat_audio_llm/audio_context_aggregator.py
pipecat_audio_llm/audio_user_turn_stop_strategy.py
pipecat_audio_llm-0.1.0.dist-info/METADATA
pipecat_audio_llm-0.1.0.dist-info/WHEEL
pipecat_audio_llm-0.1.0.dist-info/top_level.txt
pipecat_audio_llm-0.1.0.dist-info/RECORD
