Metadata-Version: 2.4
Name: pipecat-audio-llm
Version: 0.1.0
Summary: Audio-native LLM utilities for Pipecat
Author-email: Respeecher <nv@respeecher.com>
Maintainer-email: Respeecher <nv@respeecher.com>
License-Expression: BSD-2-Clause
Project-URL: Source, https://github.com/respeecher/pipecat-audio-llm
Keywords: pipecat-ai,pipecat
Classifier: Intended Audience :: Developers
Classifier: Operating System :: OS Independent
Classifier: Programming Language :: Python :: 3.10
Classifier: Programming Language :: Python :: 3.11
Classifier: Programming Language :: Python :: 3.12
Classifier: Programming Language :: Python :: 3.13
Classifier: Topic :: Software Development :: Libraries :: Python Modules
Requires-Python: >=3.10
Requires-Dist: pipecat-ai
